py_unhcr/__init__.py
py_unhcr/decorators_unhcr.py
py_unhcr/main.py
py_unhcr-0.1.2.dist-info/LICENSE
py_unhcr-0.1.2.dist-info/METADATA
py_unhcr-0.1.2.dist-info/WHEEL
py_unhcr-0.1.2.dist-info/top_level.txt
py_unhcr-0.1.2.dist-info/RECORD
