Metadata-Version: 2.1
Name: py-unhcr
Version: 0.1.2
Summary: Wrapper for the public UNHCR API, with built-in functions to make things easier
Author-email: Luis Alfredo Chaparro Gomez <luis@chapi.dev>
License: MIT License
Project-URL: Homepage, https://github.com/chapig/py-unhcr
Project-URL: Bug Tracker, https://github.com/chapig/py-unhcr/issues
Keywords: unhcr,api,refugee,asylum,humanitarian
Classifier: Programming Language :: Python :: 3
Classifier: License :: OSI Approved :: MIT License
Classifier: Operating System :: OS Independent
Classifier: Development Status :: 3 - Alpha
Classifier: Intended Audience :: Developers
Classifier: Topic :: Software Development :: Libraries :: Python Modules
Requires-Python: >=3.7
License-File: LICENSE
Requires-Dist: requests>=2.25.0
Requires-Dist: pandas>=1.0.0
